LorisBallsBasedModel/__init__.py
LorisBallsBasedModel/Layers/AttentiveTransformer.py
LorisBallsBasedModel/Layers/BoundedParaboloids.py
LorisBallsBasedModel/Layers/LSTMCell.py
LorisBallsBasedModel/Layers/MaskActivation.py
LorisBallsBasedModel/Layers/Processing.py
LorisBallsBasedModel/Layers/Step.py
LorisBallsBasedModel/Layers/UtilityLayers.py
LorisBallsBasedModel/Layers/WeightedAdd.py
LorisBallsBasedModel/Layers/__init__.py
LorisBallsBasedModel/Models/Models.py
LorisBallsBasedModel/Models/__init__.py
LorisBallsBasedModel/Tuners/HyperModelCrossValidation.py
LorisBallsBasedModel/Tuners/__init__.py
LorisBallsBasedModel-0.0.4.dist-info/LICENSE
LorisBallsBasedModel-0.0.4.dist-info/METADATA
LorisBallsBasedModel-0.0.4.dist-info/WHEEL
LorisBallsBasedModel-0.0.4.dist-info/top_level.txt
LorisBallsBasedModel-0.0.4.dist-info/RECORD
