Metadata-Version: 2.1
Name: LorisBallsBasedModel
Version: 0.0.4
Summary: A package that allows to build neural networks models using my balls.
Home-page: https://github.com/LorisPilotto/LorisBallsBasedModel
Author: Loris Pilotto
Author-email: loris.pilotto.pm@gmail.com
License: UNKNOWN
Keywords: Python,Neural Network,TensorFlow,LorisBallsBasedModel,Machine Learning
Platform: UNKNOWN
Classifier: Development Status :: 3 - Alpha
Classifier: Intended Audience :: Science/Research
Classifier: Programming Language :: Python :: 3
Classifier: Operating System :: Unix
Classifier: Operating System :: MacOS :: MacOS X
Classifier: Operating System :: Microsoft :: Windows
License-File: LICENSE
Requires-Dist: tensorflow
Requires-Dist: tensorflow-addons
Requires-Dist: keras-tuner
Requires-Dist: pandas
Requires-Dist: numpy
